baukasten/__init__.py
baukasten/config.py
baukasten/event_bus.py
baukasten/helpers.py
baukasten/logger.py
baukasten/models.py
baukasten/registry.py
baukasten-0.0.2.dist-info/METADATA
baukasten-0.0.2.dist-info/WHEEL
baukasten-0.0.2.dist-info/top_level.txt
baukasten-0.0.2.dist-info/RECORD
