Metadata-Version: 2.1
Name: baukasten
Version: 0.0.2
Summary: A plugin framework.
Home-page: https://github.com/bytebutcher/python-baukasten
Author: bytebutcher
License: GPL-3.0
Classifier: Programming Language :: Python :: 3
Classifier: Operating System :: OS Independent
Requires-Dist: toml~=0.10.2
Requires-Dist: pytest~=8.3.4
Requires-Dist: colorlog~=6.9.0
